<?xml version="1.0" encoding="UTF-8"?>
<fe:Facturae xmlns:ds="http://www.w3.org/2000/09/xmldsig#" xmlns:fe="http://www.facturae.es/Facturae/2014/v3.2.1/Facturae"><FileHeader><SchemaVersion>3.2.1</SchemaVersion><Modality>I</Modality><InvoiceIssuerType>EM</InvoiceIssuerType><Batch><BatchIdentifier>S0611001IAYE2026A02007,</BatchIdentifier><InvoicesCount>1</InvoicesCount><TotalInvoicesAmount><TotalAmount>5160.96</TotalAmount></TotalInvoicesAmount><TotalOutstandingAmount><TotalAmount>5160.96</TotalAmount></TotalOutstandingAmount><TotalExecutableAmount><TotalAmount>5160.96</TotalAmount></TotalExecutableAmount><InvoiceCurrencyCode>EUR</InvoiceCurrencyCode></Batch></FileHeader><Parties><SellerParty><TaxIdentification><PersonTypeCode>J</PersonTypeCode><ResidenceTypeCode>R</ResidenceTypeCode><TaxIdentificationNumber>B06720403</TaxIdentificationNumber></TaxIdentification><LegalEntity><CorporateName>AUTOCARES V YEGROS, S.L.</CorporateName><AddressInSpain><Address>CALLE ARQUITECTO, 10</Address><PostCode>06400</PostCode><Town>DON BENITO</Town><Province>BADAJOZ</Province><CountryCode>ESP</CountryCode></AddressInSpain><ContactDetails><Telephone>627418660</Telephone><ElectronicMail>autocaresyegros@gmail.com</ElectronicMail></ContactDetails></LegalEntity></SellerParty><BuyerParty><TaxIdentification><PersonTypeCode>J</PersonTypeCode><ResidenceTypeCode>R</ResidenceTypeCode><TaxIdentificationNumber>S0611001I</TaxIdentificationNumber></TaxIdentification><AdministrativeCentres><AdministrativeCentre><CentreCode>A11003800</CentreCode><RoleTypeCode>02</RoleTypeCode><Name>EPESEC</Name><AddressInSpain><Address>Avda Valhondo S/N. Edificio Mérida III Milenio - Módulo 5 - 2ª Planta</Address><PostCode>06800</PostCode><Town>Mérida</Town><Province>Badajoz</Province><CountryCode>ESP</CountryCode></AddressInSpain></AdministrativeCentre><AdministrativeCentre><CentreCode>A11003800</CentreCode><RoleTypeCode>03</RoleTypeCode><Name>EPESEC</Name><AddressInSpain><Address>Avda Valhondo S/N. Edificio Mérida III Milenio - Módulo 5 - 2ª Planta</Address><PostCode>06800</PostCode><Town>Mérida</Town><Province>Badajoz</Province><CountryCode>ESP</CountryCode></AddressInSpain></AdministrativeCentre><AdministrativeCentre><CentreCode>A11046195</CentreCode><RoleTypeCode>01</RoleTypeCode><Name>INTERVENCIÓN</Name><AddressInSpain><Address>Avda Valhondo S/N. Edificio Mérida III Milenio - Módulo 5 - 2ª Planta</Address><PostCode>06800</PostCode><Town>Mérida</Town><Province>Badajoz</Province><CountryCode>ESP</CountryCode></AddressInSpain></AdministrativeCentre></AdministrativeCentres><LegalEntity><CorporateName>ENTE PÚBLICO EXTREMEÑO DE SERVICIOS EDUCATIVOS COMPLEMENTARIOS</CorporateName><AddressInSpain><Address>Avda Valhondo S/N. Edificio Mérida III Milenio - Módulo 5 - 2ª Planta</Address><PostCode>06800</PostCode><Town>Mérida</Town><Province>Badajoz</Province><CountryCode>ESP</CountryCode></AddressInSpain></LegalEntity></BuyerParty></Parties><Invoices><Invoice><InvoiceHeader><InvoiceNumber>AYE2026A02007</InvoiceNumber><InvoiceSeriesCode>,</InvoiceSeriesCode><InvoiceDocumentType>FC</InvoiceDocumentType><InvoiceClass>OO</InvoiceClass></InvoiceHeader><InvoiceIssueData><IssueDate>2026-02-09</IssueDate><InvoicingPeriod><StartDate>2026-01-08</StartDate><EndDate>2026-01-31</EndDate></InvoicingPeriod><InvoiceCurrencyCode>EUR</InvoiceCurrencyCode><TaxCurrencyCode>EUR</TaxCurrencyCode><LanguageName>es</LanguageName></InvoiceIssueData><TaxesOutputs><Tax><TaxTypeCode>01</TaxTypeCode><TaxRate>10.0</TaxRate><TaxableBase><TotalAmount>4691.78</TotalAmount></TaxableBase><TaxAmount><TotalAmount>469.18</TotalAmount></TaxAmount></Tax></TaxesOutputs><InvoiceTotals><TotalGrossAmount>4691.78</TotalGrossAmount><TotalGeneralDiscounts>0.0</TotalGeneralDiscounts><TotalGeneralSurcharges>0.0</TotalGeneralSurcharges><TotalGrossAmountBeforeTaxes>4691.78</TotalGrossAmountBeforeTaxes><TotalTaxOutputs>469.18</TotalTaxOutputs><TotalTaxesWithheld>0.0</TotalTaxesWithheld><InvoiceTotal>5160.96</InvoiceTotal><TotalOutstandingAmount>5160.96</TotalOutstandingAmount><TotalExecutableAmount>5160.96</TotalExecutableAmount></InvoiceTotals><Items><InvoiceLine><ItemDescription>RUTA BA-171 ENERO CONTRATO DE EMERGENCIA TRANSPORTE ESCOLAR CURSO 2025/261</ItemDescription><Quantity>1</Quantity><UnitOfMeasure>01</UnitOfMeasure><UnitPriceWithoutTax>4691.78</UnitPriceWithoutTax><TotalCost>4691.78</TotalCost><GrossAmount>4691.78</GrossAmount><TaxesOutputs><Tax><TaxTypeCode>01</TaxTypeCode><TaxRate>10</TaxRate><TaxableBase><TotalAmount>4691.78</TotalAmount></TaxableBase><TaxAmount><TotalAmount>469.18</TotalAmount></TaxAmount></Tax></TaxesOutputs></InvoiceLine></Items></Invoice></Invoices></fe:Facturae>